controller/MPC_controller_class.py
controller/__init__.py
controller/plot_simulation.py
math_tools/Function.py
math_tools/RK4.py
math_tools/__init__.py
math_tools/data_handler_class.py
trajectory_planning/__init__.py
trajectory_planning/coupled_pol_interpolation.py
trajectory_planning/drift_checker_class.py
trajectory_planning/post_processing.py
trajectory_planning/trajectory_class.py
hopper_traj-0.1.1.dist-info/LICENSE.md
hopper_traj-0.1.1.dist-info/METADATA
hopper_traj-0.1.1.dist-info/WHEEL
hopper_traj-0.1.1.dist-info/top_level.txt
hopper_traj-0.1.1.dist-info/RECORD
