Metadata-Version: 2.1
Name: hopper-traj
Version: 0.1.1
Summary: This project comprises a trajectory generation algorithm with hardware limitaion constraints and a MPC controller to track the trajectory.
Home-page: https://github.com/brunosorban/hopper_traj
Author: Bruno Sorban
Author-email: brunosorban@gmail.com
License-File: LICENSE.md
Requires-Dist: numpy
Requires-Dist: scipy
Requires-Dist: matplotlib
Requires-Dist: sympy
Requires-Dist: mayavi
Requires-Dist: imageio
Requires-Dist: casadi
